[
  {
    "id": "1",
    "title": "Prism Core Tee",
    "price": 45,
    "description": "A premium heavyweight cotton tee with the signature Prism logo. Minimalist design for maximum impact.",
    "images": [
      "https://images.unsplash.com/photo-1521572163474-6864f9cf17ab?auto=format&fit=crop&q=80&w=800",
      "https://images.unsplash.com/photo-1583743814966-8936f5b7be1a?auto=format&fit=crop&q=80&w=800"
    ],
    "category": "T-Shirts",
    "sizes": ["S", "M", "L", "XL"],
    "isSpectrum": true,
    "spectrumImage": "https://images.unsplash.com/photo-1550684848-fac1c5b4e853?auto=format&fit=crop&q=80&w=800",
    "stockCount": 15,
    "isOutOfStock": false
  },
  {
    "id": "2",
    "title": "Spectrum Hoodie",
    "price": 85,
    "description": "Ultra-soft fleece hoodie featuring a holographic spectrum print that reacts to light.",
    "images": [
      "https://images.unsplash.com/photo-1556821840-3a63f95609a7?auto=format&fit=crop&q=80&w=800",
      "https://images.unsplash.com/photo-1578932750294-f5075e85f44a?auto=format&fit=crop&q=80&w=800"
    ],
    "category": "Hoodies",
    "sizes": ["M", "L", "XL"],
    "offer": 15,
    "isLimitedTime": true,
    "isSpectrum": true,
    "spectrumImage": "https://images.unsplash.com/photo-1618005182384-a83a8bd57fbe?auto=format&fit=crop&q=80&w=800",
    "stockCount": 8,
    "isOutOfStock": false
  },
  {
    "id": "3",
    "title": "Light-Beam Joggers",
    "price": 65,
    "description": "Technical joggers designed for movement. Reflective piping along the seams.",
    "images": [
      "https://images.unsplash.com/photo-1552346154-21d32810aba3?auto=format&fit=crop&q=80&w=800",
      "https://images.unsplash.com/photo-1542291026-7eec264c27ff?auto=format&fit=crop&q=80&w=800"
    ],
    "category": "Pants",
    "sizes": ["S", "M", "L"],
    "stockCount": 0,
    "isOutOfStock": true
  },
  {
    "id": "4",
    "title": "Prism Cap",
    "price": 30,
    "description": "Adjustable 6-panel cap with embroidered prism detail.",
    "images": [
      "https://images.unsplash.com/photo-1588850561407-ed78c282e89b?auto=format&fit=crop&q=80&w=800",
      "https://images.unsplash.com/photo-1534215754734-18e55d13e346?auto=format&fit=crop&q=80&w=800"
    ],
    "category": "Accessories",
    "sizes": ["One Size"],
    "stockCount": 25,
    "isOutOfStock": false
  }
]
